MANIFEST.in
README.md
setup.cfg
setup.py
versioneer.py
tdx/__init__.py
tdx/_version.py
tdx/config.py
tdx/engine.py
tdx/engine_stash.py
tdx/main.py
tdx/data/gbbq
tdx/data/blocknew/CX-.blk
tdx/data/blocknew/CX.blk
tdx/data/blocknew/CX1.blk
tdx/data/blocknew/DZYJ-.blk
tdx/data/blocknew/GG.blk
tdx/data/blocknew/GG1.blk
tdx/data/blocknew/GS.blk
tdx/data/blocknew/HX.blk
tdx/data/blocknew/JG-.blk
tdx/data/blocknew/LX.blk
tdx/data/blocknew/QL.blk
tdx/data/blocknew/TX-.blk
tdx/data/blocknew/XA.blk
tdx/data/blocknew/XNY-.blk
tdx/data/blocknew/XQZY.blk
tdx/data/blocknew/YGS.blk
tdx/data/blocknew/ZXG.blk
tdx/data/blocknew/ZZ.blk
tdx/data/blocknew/blocknew.cfg
tdx/data/blocknew/blocknew.clr
tdx/data/blocknew/zxgmore.dat
tdx/utils/__init__.py
tdx/utils/compat.py
tdx/utils/memoize.py
tdx/utils/paths.py
tdx/utils/util.py
tdx_wrapper.egg-info/PKG-INFO
tdx_wrapper.egg-info/SOURCES.txt
tdx_wrapper.egg-info/dependency_links.txt
tdx_wrapper.egg-info/requires.txt
tdx_wrapper.egg-info/top_level.txt